Metadata-Version: 2.4
Name: holocell
Version: 0.6.0
Summary: Architectural discovery engine for physics constants and self-healing network topologies
Author-email: Nicholas David Brown <worldbridgerstudios@gmail.com>
License: CC0-1.0
Project-URL: Homepage, https://github.com/worldbridgerstudios/HoloCell
Project-URL: Documentation, https://zenodo.org/records/18183435
Project-URL: Repository, https://github.com/worldbridgerstudios/HoloCell
Keywords: physics,constants,triangular-numbers,gene-expression-programming,fine-structure-constant,holographic,self-healing-networks,platonic-solids,graph-theory,network-topology
Classifier: Development Status :: 4 - Beta
Classifier: Intended Audience :: Science/Research
Classifier: License :: OSI Approved :: MIT License
Classifier: Programming Language :: Python :: 3
Classifier: Programming Language :: Python :: 3.9
Classifier: Programming Language :: Python :: 3.10
Classifier: Programming Language :: Python :: 3.11
Classifier: Programming Language :: Python :: 3.12
Classifier: Topic :: Scientific/Engineering :: Physics
Classifier: Topic :: Scientific/Engineering :: Mathematics
Requires-Python: >=3.9
License-File: LICENSE
Requires-Dist: gepevolver>=0.2.0
Dynamic: license-file
